<?xml version='1.0' encoding='UTF-8'?>
<import>
  <products>
    <product>
      <attribute>
        <code>31158</code>
        <value>53366-10027</value>
      </attribute>
      <attribute>
        <code>Shop_SKU</code>
        <value/>
      </attribute>
      <attribute>
        <code>Title_en</code>
        <value/>
      </attribute>
      <attribute>
        <code>EAN</code>
        <value/>
      </attribute>
      <attribute>
        <code>Brand</code>
        <value/>
      </attribute>
      <attribute>
        <code>Short_description_en</code>
        <value/>
      </attribute>
      <attribute>
        <code>Image1</code>
        <value/>
      </attribute>
      <attribute>
        <code>Image2</code>
        <value/>
      </attribute>
      <attribute>
        <code>Image3</code>
        <value/>
      </attribute>
      <attribute>
        <code>Title_no</code>
        <value/>
      </attribute>
      <attribute>
        <code>Title_dk</code>
        <value/>
      </attribute>
      <attribute>
        <code>Title_se</code>
        <value/>
      </attribute>
      <attribute>
        <code>Title_fi</code>
        <value/>
      </attribute>
      <attribute>
        <code>Short_description_no</code>
        <value/>
      </attribute>
      <attribute>
        <code>Short_description_dk</code>
        <value/>
      </attribute>
      <attribute>
        <code>Short_description_se</code>
        <value/>
      </attribute>
      <attribute>
        <code>Short_description_fi</code>
        <value/>
      </attribute>
      <attribute>
        <code>Long_description_en</code>
        <value/>
      </attribute>
      <attribute>
        <code>Long_description_no</code>
        <value/>
      </attribute>
      <attribute>
        <code>Long_description_dk</code>
        <value/>
      </attribute>
      <attribute>
        <code>Long_description_se</code>
        <value/>
      </attribute>
      <attribute>
        <code>Long_description_fi</code>
        <value/>
      </attribute>
      <attribute>
        <code>Bullet_point1_en</code>
        <value/>
      </attribute>
      <attribute>
        <code>Bullet_point1_no</code>
        <value/>
      </attribute>
      <attribute>
        <code>Bullet_point1_dk</code>
        <value/>
      </attribute>
      <attribute>
        <code>Bullet_point1_se</code>
        <value/>
      </attribute>
      <attribute>
        <code>Bullet_point1_fi</code>
        <value/>
      </attribute>
      <attribute>
        <code>Bullet_point2_en</code>
        <value/>
      </attribute>
      <attribute>
        <code>Bullet_point2_dk</code>
        <value/>
      </attribute>
      <attribute>
        <code>Bullet_point2_no</code>
        <value/>
      </attribute>
      <attribute>
        <code>Bullet_point2_se</code>
        <value/>
      </attribute>
      <attribute>
        <code>Bullet_point2_fi</code>
        <value/>
      </attribute>
      <attribute>
        <code>Bullet_point3_en</code>
        <value/>
      </attribute>
      <attribute>
        <code>Bullet_point3_no</code>
        <value/>
      </attribute>
      <attribute>
        <code>Bullet_point3_dk</code>
        <value/>
      </attribute>
      <attribute>
        <code>Bullet_point3_se</code>
        <value/>
      </attribute>
      <attribute>
        <code>Bullet_point3_fi</code>
        <value/>
      </attribute>
      <attribute>
        <code>Weight_KG</code>
        <value/>
      </attribute>
      <attribute>
        <code>Assembled_width</code>
        <value/>
      </attribute>
      <attribute>
        <code>Assembled_length</code>
        <value/>
      </attribute>
      <attribute>
        <code>Assembled_height</code>
        <value/>
      </attribute>
      <attribute>
        <code>30948</code>
        <value/>
      </attribute>
      <attribute>
        <code>30688</code>
        <value/>
      </attribute>
      <attribute>
        <code>31692</code>
        <value/>
      </attribute>
      <attribute>
        <code>30376</code>
        <value/>
      </attribute>
      <attribute>
        <code>31063</code>
        <value/>
      </attribute>
      <attribute>
        <code>30067</code>
        <value/>
      </attribute>
      <attribute>
        <code>31311</code>
        <value/>
      </attribute>
      <attribute>
        <code>30648</code>
        <value/>
      </attribute>
      <attribute>
        <code>30347</code>
        <value/>
      </attribute>
      <attribute>
        <code>30949</code>
        <value/>
      </attribute>
      <attribute>
        <code>31653</code>
        <value/>
      </attribute>
      <attribute>
        <code>30100</code>
        <value/>
      </attribute>
      <attribute>
        <code>30879</code>
        <value/>
      </attribute>
      <attribute>
        <code>30156</code>
        <value/>
      </attribute>
      <attribute>
        <code>31682</code>
        <value/>
      </attribute>
      <attribute>
        <code>30724</code>
        <value/>
      </attribute>
      <attribute>
        <code>31212</code>
        <value/>
      </attribute>
      <attribute>
        <code>30778</code>
        <value/>
      </attribute>
      <attribute>
        <code>30964</code>
        <value/>
      </attribute>
      <attribute>
        <code>TemplateGROUP</code>
        <value/>
      </attribute>
      <attribute>
        <code>31135</code>
        <value/>
      </attribute>
      <attribute>
        <code>30346</code>
        <value/>
      </attribute>
      <attribute>
        <code>30849</code>
        <value/>
      </attribute>
      <attribute>
        <code>31256</code>
        <value/>
      </attribute>
      <attribute>
        <code>31416</code>
        <value/>
      </attribute>
      <attribute>
        <code>30074</code>
        <value/>
      </attribute>
      <attribute>
        <code>31757</code>
        <value/>
      </attribute>
      <attribute>
        <code>30861</code>
        <value/>
      </attribute>
      <attribute>
        <code>30811</code>
        <value/>
      </attribute>
      <attribute>
        <code>30909</code>
        <value/>
      </attribute>
      <attribute>
        <code>31310</code>
        <value/>
      </attribute>
      <attribute>
        <code>32132</code>
        <value/>
      </attribute>
      <attribute>
        <code>31672</code>
        <value/>
      </attribute>
      <attribute>
        <code>31214</code>
        <value/>
      </attribute>
      <attribute>
        <code>30049</code>
        <value/>
      </attribute>
      <attribute>
        <code>30345</code>
        <value/>
      </attribute>
      <attribute>
        <code>30151</code>
        <value/>
      </attribute>
      <attribute>
        <code>30477</code>
        <value/>
      </attribute>
      <attribute>
        <code>31340</code>
        <value/>
      </attribute>
      <attribute>
        <code>30290</code>
        <value/>
      </attribute>
      <attribute>
        <code>33246</code>
        <value/>
      </attribute>
      <attribute>
        <code>33370</code>
        <value/>
      </attribute>
      <attribute>
        <code>33377</code>
        <value/>
      </attribute>
      <attribute>
        <code>33250</code>
        <value/>
      </attribute>
      <attribute>
        <code>33248</code>
        <value/>
      </attribute>
      <attribute>
        <code>33361</code>
        <value/>
      </attribute>
      <attribute>
        <code>33245</code>
        <value/>
      </attribute>
      <attribute>
        <code>32031</code>
        <value/>
      </attribute>
      <attribute>
        <code>33247</code>
        <value/>
      </attribute>
      <attribute>
        <code>30727</code>
        <value/>
      </attribute>
      <attribute>
        <code>31211</code>
        <value/>
      </attribute>
      <attribute>
        <code>30298</code>
        <value/>
      </attribute>
      <attribute>
        <code>33376</code>
        <value/>
      </attribute>
      <attribute>
        <code>33375</code>
        <value/>
      </attribute>
      <attribute>
        <code>30148</code>
        <value/>
      </attribute>
      <attribute>
        <code>33360</code>
        <value/>
      </attribute>
      <attribute>
        <code>33249</code>
        <value/>
      </attribute>
    </product>
  </products>
  <offers>
    <offer>
      <sku>OFFER_SKU_1</sku>
      <product-id>GTIN nr</product-id>
      <product-id-type>GTIN</product-id-type>
      <description>This is the description of my amazing offer!</description>
      <internal-description>This is the internal description of my offer.</internal-description>
      <price>1000</price>
      <price-additional-info>Price including taxes</price-additional-info>
      <quantity>1</quantity>
      <min-quantity-alert>20</min-quantity-alert>
      <state>11</state>
      <available-start-date>2012-12-25</available-start-date>
      <available-end-date>2013-05-17</available-end-date>
      <logistic-class></logistic-class>
      <discount-price>1</discount-price>
      <discount-start-date>2012-12-25</discount-start-date>
      <discount-end-date>2013-12-25</discount-end-date>
      <update-delete>UPDATE</update-delete>
    </offer>
  </offers>
</import>